{
  "resources": [
    {
      "path": "data.csv",
      "name": "data",
      "profile": "tabular-data-resource",
      "scheme": "file",
      "format": "csv",
      "hashing": "md5",
      "encoding": "utf-8",
      "schema": {
        "fields": [
          {
            "name": "Units",
            "type": "string",
            "constraints": {
              "enum": [
                "",
                "Leprosy",
                "Rabies"
              ]
            },
            "title": "Units"
          },
          {
            "name": "Value",
            "type": "number",
            "title": "Value"
          },
          {
            "name": "Year",
            "type": "integer",
            "title": "Year"
          }
        ]
      }
    }
  ],
  "profile": "data-package",
  "name": "3-3-5",
  "title": "<p> 3.3.5 Number of people requiring interventions against neglected tropical diseases <br>     3.3.5.a Leprosy"
}